nosecomplete.py
setup.py
nosecomplete.egg-info/PKG-INFO
nosecomplete.egg-info/SOURCES.txt
nosecomplete.egg-info/dependency_links.txt
nosecomplete.egg-info/entry_points.txt
nosecomplete.egg-info/requires.txt
nosecomplete.egg-info/top_level.txt