Metadata-Version: 1.1
Name: nosecomplete
Version: 0.1.1
Summary: nosecomplete is a nose plugin used for completing test names from the command line, it supports both python 2 and 3.
Home-page: https://github.com/alonho/nosecomplete
Author: Alon Horev
Author-email: alon@horev.net
License: BSD
Platform: UNKNOWN
Classifier: Development Status :: 3 - Alpha
Classifier: Intended Audience :: Developers
Classifier: Operating System :: POSIX :: Linux
Classifier: Operating System :: MacOS :: MacOS X
